pyrftl/__init__.py
pyrftl/gui_main.py
pyrftl/select_pair_successive.py
pyrftl/user_select_pair_successive.py
pyrftl/func/Lens.py
pyrftl/func/__init__.py
pyrftl/func/distances_pair_analysis.py
pyrftl/func/lens_selection.py
pyrftl/func/multiprocessing_tools.py
pyrftl/func/one_specific_pair_analysis.py
pyrftl/func/pairs.py
pyrftl/func/save.py
pyrftl/func/various_stuff.py
pyrftl/func/wavefront_pair_analysis.py
pyrftl/gui/__init__.py
pyrftl/gui/frame.py
pyrftl/gui/gui_one_pair_analysis_selector.py
pyrftl/gui/gui_pair_display.py
pyrftl/gui/gui_pair_selector.py
pyrftl/gui/gui_pair_selector_processing.py
pyrftl/gui/gui_roa_file.py
pyrftl/gui/helpbox.py
pyrftl/gui/wavefront_box.py
pyrftl/img/angle.png
pyrftl/img/config.png
pyrftl/img/focal_planes.png
pyrftl/rayopt/__init__.py
pyrftl/rayopt/analyses_test.py
pyrftl/rayopt/copy_opm.py
pyrftl/rayopt/schott.py
pyrftl-1.1.2.dist-info/METADATA
pyrftl-1.1.2.dist-info/WHEEL
pyrftl-1.1.2.dist-info/licenses/LICENSES/License_BSD3
pyrftl-1.1.2.dist-info/licenses/LICENSES/License_GNU_GPLv3
pyrftl-1.1.2.dist-info/RECORD
