Metadata-Version: 2.4
Name: pyrftl
Version: 1.1.2
Summary: A Python package to determine the best pair of lenses to use as a tube lens for remote refocusing or classical microscopy.
Project-URL: Homepage, https://gitlab.unistra.fr/opm_tools/pyrftl
Project-URL: Issues, https://codeberg.org/opm_tools/PyRFTL/issues
Project-URL: Publication, http://dx.doi.org/10.1364/OL.571058
Author: Quentin Bécar, Paul Montgomery, Amir Nahas, Maioli Vincent
License-Expression: GPL-3.0-or-later AND BSD-3-Clause
License-File: LICENSES/License_BSD3
License-File: LICENSES/License_GNU_GPLv3
Classifier: Operating System :: OS Independent
Classifier: Programming Language :: Python :: 3
Requires-Python: >=3.12
Requires-Dist: customtkinter>=5.2.2
Requires-Dist: multiprocess>=0.70.18
Requires-Dist: rayoptics>=0.9.8
